voteclarify/__init__.py
voteclarify/main.py
voteclarify/prompts.py
voteclarify-2025.12.21091112.dist-info/METADATA
voteclarify-2025.12.21091112.dist-info/WHEEL
voteclarify-2025.12.21091112.dist-info/top_level.txt
voteclarify-2025.12.21091112.dist-info/RECORD
