Metadata-Version: 2.4
Name: voteclarify
Version: 2025.12.21091112
Summary: A new package that processes user queries about why small voting or ranking projects get flagged as spam so easily. It uses natural language processing to understand the input and generates a structur
Author-email: voteclarify <hi@eugene.plus>
License: MIT
Project-URL: Homepage, https://github.com/chigwell/voteclarify
Requires-Python: >=3.9
Requires-Dist: langchain-llm7>=0.0.0
Requires-Dist: llmatch-messages>=0.0.0
Requires-Dist: langchain-core>=0.3.0
